BackupService/__main__.py
BackupService/api.py
BackupService/const.py
BackupService/robocopy_config_creator.py
BackupService/service.py
pih_bck-1.6.dist-info/METADATA
pih_bck-1.6.dist-info/WHEEL
pih_bck-1.6.dist-info/entry_points.txt
pih_bck-1.6.dist-info/top_level.txt
pih_bck-1.6.dist-info/RECORD
