Metadata-Version: 2.1
Name: pih-bck
Version: 1.6
Summary: PIH Backup service module
Home-page: https://pacifichosp.com/
Author: Nikita Karachentsev
Author-email: it@pacifichosp.com
License: MIT
Requires-Dist: ipih
